{"cameraMode":{"drawMode":0,"name":"Shaded","section":"Shading Mode"},"sceneLighting":false,"audioPlay":false,"sceneViewState":{"showFog":true,"showMaterialUpdate":false,"showSkybox":false,"showFlares":true,"showImageEffects":true,"showParticleSystems":true},"in2DMode":false,"pivot":{"x":55.25999450683594,"y":15.078033447265625,"z":5.505195617675781},"rotation":{"x":-0.15300506353378297,"y":0.5882311463356018,"z":-0.11453858017921448,"w":-0.7857867479324341},"size":91.1174545288086,"orthographic":false}